{
    "25xKerbolarSystem": 8694,
    "AlarmClock": 15274,
    "BepInEx": 124661,
    "BetterIcons": 1724,
    "BetterPartsManager": 0,
    "BetterPartsManagerLegacy": 0,
    "BetterUI": 2100,
    "Blackskyskybox": 0,
    "BurnController": 14553,
    "CelestialGlow": 7389,
    "CheatsMenu": 0,
    "Cloudy": 2331,
    "ColorPresets": 15809,
    "CommNext": 10121,
    "Commlines": 19761,
    "CommunityFixes": 43237,
    "CommunityResources": 18871,
    "CountDown": 0,
    "CustomFlags": 20437,
    "DarkMode": 2158,
    "DockingAlignmentDisplay": 23133,
    "EVAAnarchy": 13664,
    "EvenBetterTimeWarp": 14251,
    "FancyFuelTanks": 13854,
    "FlightPlan": 60978,
    "GalaxyTweaker": 16461,
    "HUMANS": 11024,
    "HeadUpDisplay": 17050,
    "HideOrbits": 13777,
    "HideVAB": 6358,
    "IVA": 1935,
    "IWishTheyMadeUICustomizable": 15764,
    "Inputbinder": 12173,
    "K2D2": 51043,
    "KESASolar": 19862,
    "KSP2PAPI": 13353,
    "KSP2PrometheusExporter": 12408,
    "Kalkulator": 13644,
    "Kapitalism": 0,
    "KapybaraSpaceProgram2": 9075,
    "KerbalHeadlamp": 10611,
    "KerbalLifeHacks": 12238,
    "KerbalLifeSupportSystem": 17298,
    "KerbalNotebook": 0,
    "KerbalSimpitKSP2": 544,
    "KerbalView": 16684,
    "KerbalWebProgram": 0,
    "KerbolExpansion": 0,
    "KerbonautManager": 16958,
    "Kesa": 24754,
    "Konfig": 0,
    "KontrolSystem2": 46239,
    "Krispy": 1504,
    "KuriosityScience": 6219,
    "LazyOrbit": 29399,
    "LazyOrbitBoosted": 15013,
    "Leek": 9864,
    "LessWobbly": 15799,
    "LuxsFlamesandOrnaments": 26325,
    "LuxsOABExtensions": 16153,
    "ManeuverNodeController": 26523,
    "MapViewFocusTargeting": 14766,
    "MicroEngineer": 59725,
    "MoreResolutions": 13860,
    "MouseFlyer": 6923,
    "NoSeizureWarning": 16130,
    "NodeManager": 52213,
    "OohShiny": 1241,
    "OrbitalSurvey": 29846,
    "PaigeBGone": 15945,
    "PartsManagerHotkey": 12381,
    "PatchManager": 44575,
    "PremonitionForSpaceWarp": 19227,
    "ProbablyAskew": 6944,
    "QuantumLoader": 0,
    "QuantumModMenu": 0,
    "QuestariaAereospace": 12366,
    "QuickMods": 6122,
    "Reflektor": 883,
    "ResonantOrbitCalculator": 21915,
    "SASed-Warp": 8805,
    "SORRY": 23240,
    "SPARKTechnologies": 13254,
    "ScaledMissions": 4992,
    "ScienceArkive": 18561,
    "ShadowIncExplorationDivision": 0,
    "ShadowUtilityLIB": 0,
    "Shoemaker": 8860,
    "ShowKSP2Events": 13371,
    "SkipSplashScreen": 13248,
    "SpaceWarp": 124661,
    "SpeedyStartup": 16350,
    "SpringCleaning": 8673,
    "SuicideBurn": 0,
    "TechTreeManager": 0,
    "TextAssetDumper": 431,
    "TexturesUtilitieseXpanded": 12760,
    "TheISSConstructionKit": 2914,
    "TheNuclearOption": 16593,
    "TillDusk": 13698,
    "ToggleNotifications": 16082,
    "TrimController": 6790,
    "UIScaler": 16508,
    "UITKforKSP2": 69884,
    "UnityExplorer": 17253,
    "UtilityUplift": 18008,
    "VSwiFT": 9550,
    "WASDForVAB": 17891,
    "WMCCModules": 9428,
    "WayfarersWingsRankRibbons": 7720,
    "WheresMyCrewCapsule": 9426,
    "Zoomer": 5614,
    "kRPC2": 13317
}