{
    "AlarmClock": 1257,
    "BepInEx": 61368,
    "BetterPartsManager": 12477,
    "BetterPartsManagerLegacy": 0,
    "Blackskyskybox": 2387,
    "BurnController": 7214,
    "CheatsMenu": 16413,
    "Commlines": 5400,
    "CommunityFixes": 20721,
    "CommunityResources": 4340,
    "CountDown": 7634,
    "CustomFlags": 11568,
    "DockingAlignmentDisplay": 7633,
    "EVAAnarchy": 6612,
    "EvenBetterTimeWarp": 6666,
    "FancyFuelTanks": 5704,
    "FlightPlan": 20819,
    "GalaxyTweaker": 8933,
    "HUMANS": 3101,
    "HeadUpDisplay": 9148,
    "HideOrbits": 6358,
    "IWishTheyMadeUICustomizable": 7213,
    "Inputbinder": 3872,
    "K2D2": 18576,
    "KESASolar": 5864,
    "KSP2PrometheusExporter": 5874,
    "Kalkulator": 6696,
    "KapybaraSpaceProgram2": 2060,
    "KerbalLifeHacks": 522,
    "KerbalLifeSupportSystem": 4119,
    "KerbalNotebook": 7183,
    "KerbalView": 8999,
    "KerbalWebProgram": 7075,
    "KerbolExpansion": 0,
    "KerbonautManager": 8660,
    "Kesa": 9031,
    "Konfig": 6896,
    "KontrolSystem2": 23723,
    "LazyOrbit": 16290,
    "LazyOrbitBoosted": 7108,
    "Leek": 3108,
    "LessWobbly": 8424,
    "LuxsFlamesandOrnaments": 11265,
    "LuxsOABExtensions": 8274,
    "ManeuverNodeController": 28318,
    "MapViewFocusTargeting": 6923,
    "MicroEngineer": 30698,
    "MoreResolutions": 7136,
    "NoSeizureWarning": 8732,
    "NodeManager": 19303,
    "OrbitalSurvey": 4806,
    "PaigeBGone": 8858,
    "PartsManagerHotkey": 5983,
    "PatchManager": 10109,
    "QuantumLoader": 3871,
    "QuantumModMenu": 3375,
    "QuestariaAereospace": 3459,
    "Reflektor": 76,
    "ResonantOrbitCalculator": 13075,
    "SORRY": 14237,
    "SPARKTechnologies": 3478,
    "ShadowIncExplorationDivision": 6733,
    "ShadowUtilityLIB": 11156,
    "ShowKSP2Events": 6397,
    "SkipSplashScreen": 3552,
    "SpaceWarp": 61368,
    "SpeedyStartup": 8961,
    "SuicideBurn": 0,
    "TechTreeManager": 2136,
    "TextAssetDumper": 28,
    "TexturesUtilitieseXpanded": 5971,
    "TheNuclearOption": 3852,
    "TillDusk": 6808,
    "ToggleNotifications": 8977,
    "UIScaler": 8431,
    "UITKforKSP2": 30240,
    "UnityExplorer": 13488,
    "UtilityUplift": 10481,
    "WASDForVAB": 8836,
    "WMCCModules": 959,
    "WheresMyCrewCapsule": 1038,
    "kRPC2": 6274
}