{
    "25xKerbolarSystem": 4884,
    "AlarmClock": 10782,
    "BepInEx": 103022,
    "BetterPartsManager": 16916,
    "BetterPartsManagerLegacy": 0,
    "Blackskyskybox": 6318,
    "BurnController": 11245,
    "CelestialGlow": 3395,
    "CheatsMenu": 21592,
    "ColorPresets": 12385,
    "CommNext": 5282,
    "Commlines": 14183,
    "CommunityFixes": 34332,
    "CommunityResources": 13357,
    "CountDown": 11766,
    "CustomFlags": 16502,
    "DarkMode": 1228,
    "DockingAlignmentDisplay": 17429,
    "EVAAnarchy": 10539,
    "EvenBetterTimeWarp": 10900,
    "FancyFuelTanks": 9915,
    "FlightPlan": 46434,
    "GalaxyTweaker": 12958,
    "HUMANS": 7583,
    "HeadUpDisplay": 13445,
    "HideOrbits": 10679,
    "HideVAB": 3187,
    "IVA": 1122,
    "IWishTheyMadeUICustomizable": 12265,
    "Inputbinder": 8595,
    "K2D2": 40535,
    "KESASolar": 14281,
    "KSP2PrometheusExporter": 9667,
    "Kalkulator": 10597,
    "Kapitalism": 157,
    "KapybaraSpaceProgram2": 6096,
    "KerbalHeadlamp": 6461,
    "KerbalLifeHacks": 7978,
    "KerbalLifeSupportSystem": 12026,
    "KerbalNotebook": 11215,
    "KerbalSimpitKSP2": 231,
    "KerbalView": 13151,
    "KerbalWebProgram": 11407,
    "KerbolExpansion": 0,
    "KerbonautManager": 13375,
    "Kesa": 18703,
    "Konfig": 11025,
    "KontrolSystem2": 36633,
    "KuriosityScience": 2205,
    "LazyOrbit": 23816,
    "LazyOrbitBoosted": 11577,
    "Leek": 7055,
    "LessWobbly": 12402,
    "LuxsFlamesandOrnaments": 20014,
    "LuxsOABExtensions": 12500,
    "ManeuverNodeController": 49030,
    "MapViewFocusTargeting": 11702,
    "MicroEngineer": 51068,
    "MoreResolutions": 10988,
    "MouseFlyer": 3675,
    "NoSeizureWarning": 12915,
    "NodeManager": 41108,
    "OrbitalSurvey": 23745,
    "PaigeBGone": 12762,
    "PartsManagerHotkey": 9722,
    "PatchManager": 34606,
    "PremonitionForSpaceWarp": 11619,
    "ProbablyAskew": 3717,
    "QuantumLoader": 7768,
    "QuantumModMenu": 7138,
    "QuestariaAereospace": 8523,
    "QuickMods": 2227,
    "Reflektor": 449,
    "ResonantOrbitCalculator": 17948,
    "SASed-Warp": 5216,
    "SORRY": 18965,
    "SPARKTechnologies": 8755,
    "ScaledMissions": 1765,
    "ScienceArkive": 13923,
    "ShadowIncExplorationDivision": 11306,
    "ShadowUtilityLIB": 17212,
    "Shoemaker": 4607,
    "ShowKSP2Events": 10386,
    "SkipSplashScreen": 9584,
    "SpaceWarp": 103022,
    "SpeedyStartup": 13117,
    "SpringCleaning": 3410,
    "SuicideBurn": 0,
    "TechTreeManager": 6733,
    "TextAssetDumper": 187,
    "TexturesUtilitieseXpanded": 9770,
    "TheNuclearOption": 11269,
    "TillDusk": 10704,
    "ToggleNotifications": 12919,
    "TrimController": 3787,
    "UIScaler": 13032,
    "UITKforKSP2": 56343,
    "UnityExplorer": 14040,
    "UtilityUplift": 14620,
    "VSwiFT": 4171,
    "WASDForVAB": 14037,
    "WMCCModules": 5862,
    "WayfarersWingsRankRibbons": 3845,
    "WheresMyCrewCapsule": 5814,
    "Zoomer": 1927,
    "kRPC2": 10251
}