{
    "BepInEx": 25281,
    "BetterPartsManager": 8648,
    "BurnController": 4007,
    "CheatsMenu": 11127,
    "Commlines": 530,
    "CommunityFixes": 11000,
    "CountDown": 4365,
    "CustomFlags": 7332,
    "DockingAlignmentDisplay": 304,
    "EVAAnarchy": 3527,
    "EvenBetterTimeWarp": 3246,
    "FancyFuelTanks": 864,
    "FlightPlan": 8555,
    "GalaxyTweaker": 5741,
    "HeadUpDisplay": 5886,
    "IWishTheyMadeUICustomizable": 3398,
    "Inputbinder": 483,
    "K2D2": 7681,
    "KSP2PrometheusExporter": 2955,
    "Kalkulator": 3634,
    "KerbalNotebook": 4068,
    "KerbalView": 5765,
    "KerbalWebProgram": 3615,
    "KerbonautManager": 4622,
    "Kesa": 2686,
    "Konfig": 2968,
    "KontrolSystem2": 15108,
    "LazyOrbit": 12173,
    "LazyOrbitBoosted": 2202,
    "LessWobbly": 5095,
    "LuxsFlamesandOrnaments": 4810,
    "LuxsOABExtensions": 4795,
    "ManeuverNodeController": 16208,
    "MapViewFocusTargeting": 3267,
    "MicroEngineer": 18419,
    "MoreResolutions": 4048,
    "NoSeizureWarning": 5294,
    "NodeManager": 6844,
    "PaigeBGone": 625,
    "PartsManagerHotkey": 3125,
    "QuantumLoader": 511,
    "QuantumModMenu": 444,
    "ResonantOrbitCalculator": 8905,
    "SORRY": 9782,
    "ShadowIncExplorationDivision": 2807,
    "ShadowUtilityLIB": 5256,
    "ShowKSP2Events": 3206,
    "SpaceWarp": 25281,
    "SpeedyStartup": 5482,
    "SuicideBurn": 5308,
    "TexturesUtilitieseXpanded": 3038,
    "TillDusk": 3686,
    "ToggleNotifications": 5701,
    "UIScaler": 5327,
    "UITKforKSP2": 10318,
    "UtilityUplift": 7043,
    "WASDForVAB": 5553,
    "kRPC2": 3079
}