{
    "25xKerbolarSystem": 9461,
    "AlarmClock": 16440,
    "BepInEx": 129625,
    "BetterIcons": 2594,
    "BetterPartsManager": 0,
    "BetterPartsManagerLegacy": 0,
    "BetterUI": 3117,
    "Blackskyskybox": 0,
    "BurnController": 15312,
    "CelestialGlow": 8234,
    "CheatsMenu": 0,
    "Cloudy": 3954,
    "ColorPresets": 16532,
    "CommNext": 11110,
    "Commlines": 20820,
    "CommunityFixes": 45615,
    "CommunityResources": 20126,
    "CountDown": 0,
    "CustomFlags": 21256,
    "DarkMode": 2375,
    "DebugTools": 1236,
    "DockingAlignmentDisplay": 24417,
    "EVAAnarchy": 14337,
    "EvenBetterTimeWarp": 14969,
    "FancyFuelTanks": 14750,
    "FlightPlan": 63660,
    "GalaxyTweaker": 17252,
    "HUMANS": 11657,
    "HeadUpDisplay": 17755,
    "HideOrbits": 14384,
    "HideVAB": 7067,
    "IVA": 2221,
    "IWishTheyMadeUICustomizable": 16411,
    "Inputbinder": 12886,
    "K2D2": 53240,
    "KESASolar": 21023,
    "KSP2PAPI": 14184,
    "KSP2PrometheusExporter": 12887,
    "Kalkulator": 14362,
    "Kapitalism": 0,
    "KapybaraSpaceProgram2": 9617,
    "KerbalHeadlamp": 11424,
    "KerbalLifeHacks": 13206,
    "KerbalLifeSupportSystem": 18641,
    "KerbalNotebook": 0,
    "KerbalSimpitKSP2": 617,
    "KerbalView": 17504,
    "KerbalWebProgram": 0,
    "KerbolExpansion": 0,
    "KerbonautManager": 17792,
    "Kesa": 26077,
    "Konfig": 0,
    "KontrolSystem2": 48757,
    "Krispy": 3111,
    "KuriosityScience": 6924,
    "LazyOrbit": 30503,
    "LazyOrbitBoosted": 15688,
    "Leek": 10373,
    "LessWobbly": 16545,
    "LuxsFlamesandOrnaments": 27858,
    "LuxsOABExtensions": 16927,
    "ManeuverNodeController": 32533,
    "MapViewFocusTargeting": 15351,
    "Meltdown": 1418,
    "MicroEngineer": 61786,
    "MissionTreeExpanded": 1740,
    "MoreResolutions": 14408,
    "MouseFlyer": 7541,
    "NoSeizureWarning": 16790,
    "NodeManager": 54493,
    "OohShiny": 2535,
    "OrbitalSurvey": 31053,
    "PaigeBGone": 16628,
    "PartsManagerHotkey": 12839,
    "PatchManager": 47355,
    "Planety": 2130,
    "PremonitionForSpaceWarp": 21169,
    "ProbablyAskew": 7635,
    "QuantumLoader": 0,
    "QuantumModMenu": 0,
    "QuestariaAereospace": 13245,
    "QuickMods": 6987,
    "Reflektor": 985,
    "ResonantOrbitCalculator": 22908,
    "SASed-Warp": 9516,
    "SORRY": 24195,
    "SPARKTechnologies": 14143,
    "ScaledMissions": 5553,
    "ScienceArkive": 19571,
    "ShadowIncExplorationDivision": 0,
    "ShadowUtilityLIB": 0,
    "Shoemaker": 10121,
    "ShowKSP2Events": 13926,
    "SkipSplashScreen": 13927,
    "SpaceWarp": 129625,
    "SpeedyStartup": 17025,
    "SpringCleaning": 9866,
    "SuicideBurn": 0,
    "TechTreeManager": 0,
    "TextAssetDumper": 505,
    "TexturesUtilitieseXpanded": 13403,
    "TheISSConstructionKit": 4564,
    "TheNuclearOption": 17799,
    "TillDusk": 14266,
    "ToggleNotifications": 16702,
    "TrimController": 7398,
    "UIScaler": 17171,
    "UITKforKSP2": 73253,
    "UnityExplorer": 17825,
    "UtilityUplift": 18713,
    "VSwiFT": 10770,
    "WASDForVAB": 18625,
    "WMCCModules": 10149,
    "WayfarersWingsRankRibbons": 8420,
    "WheresMyCrewCapsule": 10113,
    "Zoomer": 6292,
    "kRPC2": 13876
}