{
    "25xKerbolarSystem": 6331,
    "AlarmClock": 12249,
    "BepInEx": 111773,
    "BetterPartsManager": 18163,
    "BetterPartsManagerLegacy": 0,
    "Blackskyskybox": 7179,
    "BurnController": 12463,
    "CelestialGlow": 4962,
    "CheatsMenu": 23075,
    "ColorPresets": 13661,
    "CommNext": 7266,
    "Commlines": 16500,
    "CommunityFixes": 37183,
    "CommunityResources": 15555,
    "CountDown": 12914,
    "CustomFlags": 17908,
    "DarkMode": 1588,
    "DockingAlignmentDisplay": 19703,
    "EVAAnarchy": 11714,
    "EvenBetterTimeWarp": 12069,
    "FancyFuelTanks": 11213,
    "FlightPlan": 52679,
    "GalaxyTweaker": 14182,
    "HUMANS": 8838,
    "HeadUpDisplay": 14835,
    "HideOrbits": 11870,
    "HideVAB": 4388,
    "IVA": 1236,
    "IWishTheyMadeUICustomizable": 13591,
    "Inputbinder": 9953,
    "K2D2": 45017,
    "KESASolar": 16525,
    "KSP2PrometheusExporter": 10723,
    "Kalkulator": 11763,
    "Kapitalism": 1790,
    "KapybaraSpaceProgram2": 7232,
    "KerbalHeadlamp": 8147,
    "KerbalLifeHacks": 9646,
    "KerbalLifeSupportSystem": 13896,
    "KerbalNotebook": 12323,
    "KerbalSimpitKSP2": 326,
    "KerbalView": 14334,
    "KerbalWebProgram": 12633,
    "KerbolExpansion": 0,
    "KerbonautManager": 14677,
    "Kesa": 20973,
    "Konfig": 12135,
    "KontrolSystem2": 41778,
    "KuriosityScience": 3801,
    "LazyOrbit": 25919,
    "LazyOrbitBoosted": 12793,
    "Leek": 8127,
    "LessWobbly": 13633,
    "LuxsFlamesandOrnaments": 22370,
    "LuxsOABExtensions": 13698,
    "ManeuverNodeController": 37878,
    "MapViewFocusTargeting": 12939,
    "MicroEngineer": 54428,
    "MoreResolutions": 12066,
    "MouseFlyer": 4921,
    "NoSeizureWarning": 14061,
    "NodeManager": 45226,
    "OrbitalSurvey": 26129,
    "PaigeBGone": 13946,
    "PartsManagerHotkey": 10758,
    "PatchManager": 38187,
    "PremonitionForSpaceWarp": 14585,
    "ProbablyAskew": 5036,
    "QuantumLoader": 8883,
    "QuantumModMenu": 8182,
    "QuestariaAereospace": 9818,
    "QuickMods": 3732,
    "Reflektor": 567,
    "ResonantOrbitCalculator": 19385,
    "SASed-Warp": 6614,
    "SORRY": 20373,
    "SPARKTechnologies": 10513,
    "ScaledMissions": 2984,
    "ScienceArkive": 15873,
    "ShadowIncExplorationDivision": 12568,
    "ShadowUtilityLIB": 19010,
    "Shoemaker": 5978,
    "ShowKSP2Events": 11508,
    "SkipSplashScreen": 11032,
    "SpaceWarp": 111773,
    "SpeedyStartup": 14252,
    "SpringCleaning": 5429,
    "SuicideBurn": 0,
    "TechTreeManager": 7984,
    "TextAssetDumper": 262,
    "TexturesUtilitieseXpanded": 10915,
    "TheNuclearOption": 13317,
    "TillDusk": 11806,
    "ToggleNotifications": 14119,
    "TrimController": 4903,
    "UIScaler": 14410,
    "UITKforKSP2": 61329,
    "UnityExplorer": 14680,
    "UtilityUplift": 15806,
    "VSwiFT": 6306,
    "WASDForVAB": 15514,
    "WMCCModules": 7264,
    "WayfarersWingsRankRibbons": 5413,
    "WheresMyCrewCapsule": 7207,
    "Zoomer": 3358,
    "kRPC2": 11473
}