{
    "AlarmClock": 842,
    "BepInEx": 60879,
    "BetterPartsManager": 12409,
    "BetterPartsManagerLegacy": 0,
    "Blackskyskybox": 2328,
    "BurnController": 7152,
    "CheatsMenu": 16328,
    "Commlines": 5245,
    "CommunityFixes": 20415,
    "CommunityResources": 4236,
    "CountDown": 7573,
    "CustomFlags": 11489,
    "DockingAlignmentDisplay": 7227,
    "EVAAnarchy": 6556,
    "EvenBetterTimeWarp": 6602,
    "FancyFuelTanks": 5639,
    "FlightPlan": 20520,
    "GalaxyTweaker": 8875,
    "HUMANS": 3028,
    "HeadUpDisplay": 9087,
    "HideOrbits": 6263,
    "IWishTheyMadeUICustomizable": 7120,
    "Inputbinder": 3801,
    "K2D2": 18155,
    "KESASolar": 5723,
    "KSP2PrometheusExporter": 5820,
    "Kalkulator": 6635,
    "KapybaraSpaceProgram2": 1999,
    "KerbalLifeHacks": 312,
    "KerbalLifeSupportSystem": 4017,
    "KerbalNotebook": 7130,
    "KerbalView": 8937,
    "KerbalWebProgram": 7006,
    "KerbolExpansion": 0,
    "KerbonautManager": 8562,
    "Kesa": 8893,
    "Konfig": 6830,
    "KontrolSystem2": 23561,
    "LazyOrbit": 16215,
    "LazyOrbitBoosted": 7030,
    "Leek": 3047,
    "LessWobbly": 8365,
    "LuxsFlamesandOrnaments": 11103,
    "LuxsOABExtensions": 8215,
    "ManeuverNodeController": 28033,
    "MapViewFocusTargeting": 6842,
    "MicroEngineer": 30433,
    "MoreResolutions": 7077,
    "NoSeizureWarning": 8667,
    "NodeManager": 18975,
    "OrbitalSurvey": 4560,
    "PaigeBGone": 8800,
    "PartsManagerHotkey": 5928,
    "PatchManager": 9386,
    "QuantumLoader": 3812,
    "QuantumModMenu": 3319,
    "QuestariaAereospace": 3398,
    "Reflektor": 68,
    "ResonantOrbitCalculator": 13000,
    "SORRY": 14162,
    "SPARKTechnologies": 3408,
    "ShadowIncExplorationDivision": 6672,
    "ShadowUtilityLIB": 11045,
    "ShowKSP2Events": 6341,
    "SkipSplashScreen": 3494,
    "SpaceWarp": 60879,
    "SpeedyStartup": 8892,
    "SuicideBurn": 0,
    "TechTreeManager": 2065,
    "TextAssetDumper": 24,
    "TexturesUtilitieseXpanded": 5917,
    "TheNuclearOption": 3786,
    "TillDusk": 6751,
    "ToggleNotifications": 8916,
    "UIScaler": 8372,
    "UITKforKSP2": 29761,
    "UnityExplorer": 13478,
    "UtilityUplift": 10417,
    "WASDForVAB": 8774,
    "WMCCModules": 881,
    "WheresMyCrewCapsule": 955,
    "kRPC2": 6218
}