{
    "25xKerbolarSystem": 8258,
    "AlarmClock": 14618,
    "BepInEx": 122174,
    "BetterIcons": 1227,
    "BetterPartsManager": 0,
    "BetterPartsManagerLegacy": 0,
    "BetterUI": 1526,
    "Blackskyskybox": 0,
    "BurnController": 14152,
    "CelestialGlow": 6937,
    "CheatsMenu": 0,
    "Cloudy": 1367,
    "ColorPresets": 15409,
    "CommNext": 9592,
    "Commlines": 19171,
    "CommunityFixes": 42000,
    "CommunityResources": 18241,
    "CountDown": 0,
    "CustomFlags": 19958,
    "DarkMode": 2051,
    "DockingAlignmentDisplay": 22501,
    "EVAAnarchy": 13319,
    "EvenBetterTimeWarp": 13815,
    "FancyFuelTanks": 13318,
    "FlightPlan": 59529,
    "GalaxyTweaker": 16056,
    "HUMANS": 10643,
    "HeadUpDisplay": 16628,
    "HideOrbits": 13446,
    "HideVAB": 6000,
    "IVA": 1773,
    "IWishTheyMadeUICustomizable": 15380,
    "Inputbinder": 11756,
    "K2D2": 49844,
    "KESASolar": 19213,
    "KSP2PAPI": 12897,
    "KSP2PrometheusExporter": 12107,
    "Kalkulator": 13311,
    "Kapitalism": 0,
    "KapybaraSpaceProgram2": 8736,
    "KerbalHeadlamp": 10173,
    "KerbalLifeHacks": 11745,
    "KerbalLifeSupportSystem": 16566,
    "KerbalNotebook": 0,
    "KerbalSimpitKSP2": 506,
    "KerbalView": 16227,
    "KerbalWebProgram": 0,
    "KerbolExpansion": 0,
    "KerbonautManager": 16529,
    "Kesa": 23983,
    "Konfig": 0,
    "KontrolSystem2": 45532,
    "Krispy": 545,
    "KuriosityScience": 5780,
    "LazyOrbit": 28781,
    "LazyOrbitBoosted": 14597,
    "Leek": 9552,
    "LessWobbly": 15380,
    "LuxsFlamesandOrnaments": 25523,
    "LuxsOABExtensions": 15678,
    "ManeuverNodeController": 24338,
    "MapViewFocusTargeting": 14436,
    "MicroEngineer": 58500,
    "MoreResolutions": 13524,
    "MouseFlyer": 6528,
    "NoSeizureWarning": 15725,
    "NodeManager": 50936,
    "OohShiny": 481,
    "OrbitalSurvey": 29139,
    "PaigeBGone": 15559,
    "PartsManagerHotkey": 12082,
    "PatchManager": 43196,
    "PremonitionForSpaceWarp": 18281,
    "ProbablyAskew": 6593,
    "QuantumLoader": 0,
    "QuantumModMenu": 0,
    "QuestariaAereospace": 11854,
    "QuickMods": 5720,
    "Reflektor": 830,
    "ResonantOrbitCalculator": 21436,
    "SASed-Warp": 8403,
    "SORRY": 22624,
    "SPARKTechnologies": 12719,
    "ScaledMissions": 4648,
    "ScienceArkive": 18018,
    "ShadowIncExplorationDivision": 0,
    "ShadowUtilityLIB": 0,
    "Shoemaker": 8211,
    "ShowKSP2Events": 13039,
    "SkipSplashScreen": 12844,
    "SpaceWarp": 122174,
    "SpeedyStartup": 15947,
    "SpringCleaning": 8065,
    "SuicideBurn": 0,
    "TechTreeManager": 0,
    "TextAssetDumper": 404,
    "TexturesUtilitieseXpanded": 12419,
    "TheISSConstructionKit": 2178,
    "TheNuclearOption": 15998,
    "TillDusk": 13328,
    "ToggleNotifications": 15728,
    "TrimController": 6436,
    "UIScaler": 16138,
    "UITKforKSP2": 68206,
    "UnityExplorer": 16968,
    "UtilityUplift": 17583,
    "VSwiFT": 8939,
    "WASDForVAB": 17414,
    "WMCCModules": 9030,
    "WayfarersWingsRankRibbons": 7308,
    "WheresMyCrewCapsule": 9017,
    "Zoomer": 5204,
    "kRPC2": 13004
}