{
    "25xKerbolarSystem": 1811,
    "AlarmClock": 6831,
    "BepInEx": 74414,
    "BetterPartsManager": 14115,
    "BetterPartsManagerLegacy": 0,
    "Blackskyskybox": 3869,
    "BurnController": 8714,
    "CheatsMenu": 18291,
    "ColorPresets": 9599,
    "Commlines": 8669,
    "CommunityFixes": 25028,
    "CommunityResources": 7447,
    "CountDown": 9228,
    "CustomFlags": 13354,
    "DarkMode": 290,
    "DockingAlignmentDisplay": 11460,
    "EVAAnarchy": 8057,
    "EvenBetterTimeWarp": 8248,
    "FancyFuelTanks": 7235,
    "FlightPlan": 26355,
    "GalaxyTweaker": 10403,
    "HUMANS": 4745,
    "HeadUpDisplay": 10643,
    "HideOrbits": 8143,
    "HideVAB": 655,
    "IVA": 787,
    "IWishTheyMadeUICustomizable": 9145,
    "Inputbinder": 5572,
    "K2D2": 26329,
    "KESASolar": 9046,
    "KSP2PrometheusExporter": 7292,
    "Kalkulator": 8142,
    "KapybaraSpaceProgram2": 3549,
    "KerbalHeadlamp": 2419,
    "KerbalLifeHacks": 3681,
    "KerbalLifeSupportSystem": 7273,
    "KerbalNotebook": 8707,
    "KerbalSimpitKSP2": 44,
    "KerbalView": 10539,
    "KerbalWebProgram": 8716,
    "KerbolExpansion": 0,
    "KerbonautManager": 10590,
    "Kesa": 12778,
    "Konfig": 8535,
    "KontrolSystem2": 27798,
    "LazyOrbit": 18527,
    "LazyOrbitBoosted": 8826,
    "Leek": 4619,
    "LessWobbly": 9892,
    "LuxsFlamesandOrnaments": 14485,
    "LuxsOABExtensions": 9820,
    "ManeuverNodeController": 33799,
    "MapViewFocusTargeting": 8727,
    "MicroEngineer": 38397,
    "MoreResolutions": 8567,
    "MouseFlyer": 688,
    "NoSeizureWarning": 10322,
    "NodeManager": 25551,
    "OrbitalSurvey": 11709,
    "PaigeBGone": 10316,
    "PartsManagerHotkey": 7372,
    "PatchManager": 19771,
    "PremonitionForSpaceWarp": 2949,
    "ProbablyAskew": 774,
    "QuantumLoader": 5308,
    "QuantumModMenu": 4778,
    "QuestariaAereospace": 5548,
    "Reflektor": 245,
    "ResonantOrbitCalculator": 14876,
    "SASed-Warp": 1660,
    "SORRY": 15916,
    "SPARKTechnologies": 5992,
    "ScienceArkive": 5405,
    "ShadowIncExplorationDivision": 8498,
    "ShadowUtilityLIB": 13549,
    "Shoemaker": 1728,
    "ShowKSP2Events": 7884,
    "SkipSplashScreen": 5497,
    "SpaceWarp": 74414,
    "SpeedyStartup": 10528,
    "SuicideBurn": 0,
    "TechTreeManager": 3882,
    "TextAssetDumper": 90,
    "TexturesUtilitieseXpanded": 7383,
    "TheNuclearOption": 6485,
    "TillDusk": 8250,
    "ToggleNotifications": 10425,
    "TrimController": 1160,
    "UIScaler": 10014,
    "UITKforKSP2": 40960,
    "UnityExplorer": 13722,
    "UtilityUplift": 11991,
    "WASDForVAB": 10365,
    "WMCCModules": 2842,
    "WheresMyCrewCapsule": 2827,
    "kRPC2": 7712
}