{
    "BepInEx": 26342,
    "BetterPartsManager": 9081,
    "BetterPartsManagerLegacy": 100,
    "BurnController": 4167,
    "CheatsMenu": 11461,
    "Commlines": 799,
    "CommunityFixes": 11387,
    "CountDown": 4551,
    "CustomFlags": 7541,
    "DockingAlignmentDisplay": 634,
    "EVAAnarchy": 3688,
    "EvenBetterTimeWarp": 3464,
    "FancyFuelTanks": 1221,
    "FlightPlan": 9094,
    "GalaxyTweaker": 5910,
    "HeadUpDisplay": 6053,
    "IWishTheyMadeUICustomizable": 3586,
    "Inputbinder": 667,
    "K2D2": 7991,
    "KSP2PrometheusExporter": 3103,
    "Kalkulator": 3786,
    "KerbalNotebook": 4245,
    "KerbalView": 5945,
    "KerbalWebProgram": 3790,
    "KerbonautManager": 4785,
    "Kesa": 3099,
    "Konfig": 3167,
    "KontrolSystem2": 15421,
    "LazyOrbit": 12422,
    "LazyOrbitBoosted": 2517,
    "LessWobbly": 5280,
    "LuxsFlamesandOrnaments": 5169,
    "LuxsOABExtensions": 5054,
    "ManeuverNodeController": 16767,
    "MapViewFocusTargeting": 3430,
    "MicroEngineer": 18838,
    "MoreResolutions": 4225,
    "NoSeizureWarning": 5510,
    "NodeManager": 7279,
    "PaigeBGone": 674,
    "PartsManagerHotkey": 3275,
    "QuantumLoader": 835,
    "QuantumModMenu": 632,
    "QuestariaAereospace": 186,
    "ResonantOrbitCalculator": 9157,
    "SORRY": 10130,
    "ShadowIncExplorationDivision": 3069,
    "ShadowUtilityLIB": 5569,
    "ShowKSP2Events": 3384,
    "SpaceWarp": 26342,
    "SpeedyStartup": 5717,
    "SuicideBurn": 5536,
    "TexturesUtilitieseXpanded": 3191,
    "TillDusk": 3895,
    "ToggleNotifications": 5888,
    "UIScaler": 5479,
    "UITKforKSP2": 11054,
    "UtilityUplift": 7268,
    "WASDForVAB": 5746,
    "kRPC2": 3232
}