{
    "25xKerbolarSystem": 7833,
    "AlarmClock": 14079,
    "BepInEx": 119787,
    "BetterIcons": 753,
    "BetterPartsManager": 0,
    "BetterPartsManagerLegacy": 0,
    "BetterUI": 974,
    "Blackskyskybox": 0,
    "BurnController": 13774,
    "CelestialGlow": 6509,
    "CheatsMenu": 0,
    "Cloudy": 627,
    "ColorPresets": 15030,
    "CommNext": 9111,
    "Commlines": 18640,
    "CommunityFixes": 40866,
    "CommunityResources": 17666,
    "CountDown": 0,
    "CustomFlags": 19483,
    "DarkMode": 1968,
    "DockingAlignmentDisplay": 21851,
    "EVAAnarchy": 12969,
    "EvenBetterTimeWarp": 13406,
    "FancyFuelTanks": 12819,
    "FlightPlan": 58068,
    "GalaxyTweaker": 15616,
    "HUMANS": 10250,
    "HeadUpDisplay": 16175,
    "HideOrbits": 13102,
    "HideVAB": 5641,
    "IVA": 1617,
    "IWishTheyMadeUICustomizable": 14972,
    "Inputbinder": 11356,
    "K2D2": 48808,
    "KESASolar": 18542,
    "KSP2PAPI": 12455,
    "KSP2PrometheusExporter": 11802,
    "Kalkulator": 12975,
    "Kapitalism": 0,
    "KapybaraSpaceProgram2": 8397,
    "KerbalHeadlamp": 9751,
    "KerbalLifeHacks": 11266,
    "KerbalLifeSupportSystem": 15996,
    "KerbalNotebook": 0,
    "KerbalSimpitKSP2": 458,
    "KerbalView": 15733,
    "KerbalWebProgram": 0,
    "KerbolExpansion": 0,
    "KerbonautManager": 16109,
    "Kesa": 23203,
    "Konfig": 0,
    "KontrolSystem2": 44379,
    "KuriosityScience": 5361,
    "LazyOrbit": 28168,
    "LazyOrbitBoosted": 14186,
    "Leek": 9239,
    "LessWobbly": 15000,
    "LuxsFlamesandOrnaments": 24779,
    "LuxsOABExtensions": 15189,
    "ManeuverNodeController": 22641,
    "MapViewFocusTargeting": 14100,
    "MicroEngineer": 57646,
    "MoreResolutions": 13182,
    "MouseFlyer": 6180,
    "NoSeizureWarning": 15318,
    "NodeManager": 49770,
    "OrbitalSurvey": 28486,
    "PaigeBGone": 15202,
    "PartsManagerHotkey": 11788,
    "PatchManager": 42042,
    "PremonitionForSpaceWarp": 17393,
    "ProbablyAskew": 6257,
    "QuantumLoader": 0,
    "QuantumModMenu": 0,
    "QuestariaAereospace": 11384,
    "QuickMods": 5338,
    "Reflektor": 757,
    "ResonantOrbitCalculator": 20985,
    "SASed-Warp": 7993,
    "SORRY": 22072,
    "SPARKTechnologies": 12221,
    "ScaledMissions": 4319,
    "ScienceArkive": 17576,
    "ShadowIncExplorationDivision": 0,
    "ShadowUtilityLIB": 0,
    "Shoemaker": 7616,
    "ShowKSP2Events": 12716,
    "SkipSplashScreen": 12460,
    "SpaceWarp": 119787,
    "SpeedyStartup": 15532,
    "SpringCleaning": 7470,
    "SuicideBurn": 0,
    "TechTreeManager": 0,
    "TextAssetDumper": 380,
    "TexturesUtilitieseXpanded": 12080,
    "TheISSConstructionKit": 1384,
    "TheNuclearOption": 15392,
    "TillDusk": 12982,
    "ToggleNotifications": 15372,
    "TrimController": 6086,
    "UIScaler": 15777,
    "UITKforKSP2": 66612,
    "UnityExplorer": 16464,
    "UtilityUplift": 17156,
    "VSwiFT": 8361,
    "WASDForVAB": 16951,
    "WMCCModules": 8647,
    "WayfarersWingsRankRibbons": 6903,
    "WheresMyCrewCapsule": 8623,
    "Zoomer": 4818,
    "kRPC2": 12689
}