{
    "25xKerbolarSystem": 6142,
    "AlarmClock": 12061,
    "BepInEx": 110931,
    "BetterPartsManager": 18011,
    "BetterPartsManagerLegacy": 0,
    "Blackskyskybox": 7040,
    "BurnController": 12291,
    "CelestialGlow": 4763,
    "CheatsMenu": 22896,
    "ColorPresets": 13469,
    "CommNext": 7031,
    "Commlines": 16288,
    "CommunityFixes": 36915,
    "CommunityResources": 15312,
    "CountDown": 12776,
    "CustomFlags": 17723,
    "DarkMode": 1527,
    "DockingAlignmentDisplay": 19450,
    "EVAAnarchy": 11546,
    "EvenBetterTimeWarp": 11918,
    "FancyFuelTanks": 11030,
    "FlightPlan": 30944,
    "GalaxyTweaker": 14008,
    "HUMANS": 8689,
    "HeadUpDisplay": 14675,
    "HideOrbits": 11700,
    "HideVAB": 4217,
    "IVA": 1214,
    "IWishTheyMadeUICustomizable": 13438,
    "Inputbinder": 9773,
    "K2D2": 44618,
    "KESASolar": 16309,
    "KSP2PrometheusExporter": 10593,
    "Kalkulator": 11595,
    "Kapitalism": 1625,
    "KapybaraSpaceProgram2": 7086,
    "KerbalHeadlamp": 7942,
    "KerbalLifeHacks": 9450,
    "KerbalLifeSupportSystem": 13664,
    "KerbalNotebook": 12186,
    "KerbalSimpitKSP2": 310,
    "KerbalView": 14183,
    "KerbalWebProgram": 12484,
    "KerbolExpansion": 0,
    "KerbonautManager": 14484,
    "Kesa": 20758,
    "Konfig": 11991,
    "KontrolSystem2": 41592,
    "KuriosityScience": 3631,
    "LazyOrbit": 25657,
    "LazyOrbitBoosted": 12639,
    "Leek": 7992,
    "LessWobbly": 13454,
    "LuxsFlamesandOrnaments": 22102,
    "LuxsOABExtensions": 13543,
    "ManeuverNodeController": 37359,
    "MapViewFocusTargeting": 12796,
    "MicroEngineer": 54133,
    "MoreResolutions": 11927,
    "MouseFlyer": 4768,
    "NoSeizureWarning": 13911,
    "NodeManager": 44435,
    "OrbitalSurvey": 25909,
    "PaigeBGone": 13770,
    "PartsManagerHotkey": 10628,
    "PatchManager": 37859,
    "PremonitionForSpaceWarp": 14294,
    "ProbablyAskew": 4866,
    "QuantumLoader": 8746,
    "QuantumModMenu": 8054,
    "QuestariaAereospace": 9644,
    "QuickMods": 3544,
    "Reflektor": 536,
    "ResonantOrbitCalculator": 19194,
    "SASed-Warp": 6466,
    "SORRY": 20196,
    "SPARKTechnologies": 10310,
    "ScaledMissions": 2839,
    "ScienceArkive": 15663,
    "ShadowIncExplorationDivision": 12404,
    "ShadowUtilityLIB": 18820,
    "Shoemaker": 5800,
    "ShowKSP2Events": 11375,
    "SkipSplashScreen": 10878,
    "SpaceWarp": 110931,
    "SpeedyStartup": 14112,
    "SpringCleaning": 5235,
    "SuicideBurn": 0,
    "TechTreeManager": 7839,
    "TextAssetDumper": 243,
    "TexturesUtilitieseXpanded": 10748,
    "TheNuclearOption": 13061,
    "TillDusk": 11672,
    "ToggleNotifications": 13958,
    "TrimController": 4759,
    "UIScaler": 14209,
    "UITKforKSP2": 60810,
    "UnityExplorer": 14642,
    "UtilityUplift": 15667,
    "VSwiFT": 6077,
    "WASDForVAB": 15353,
    "WMCCModules": 7078,
    "WayfarersWingsRankRibbons": 5211,
    "WheresMyCrewCapsule": 7021,
    "Zoomer": 3204,
    "kRPC2": 11285
}