{
    "25xKerbolarSystem": 1159,
    "AlarmClock": 5438,
    "BepInEx": 69343,
    "BetterPartsManager": 13529,
    "BetterPartsManagerLegacy": 0,
    "Blackskyskybox": 3343,
    "BurnController": 8171,
    "CheatsMenu": 17595,
    "ColorPresets": 8866,
    "Commlines": 7562,
    "CommunityFixes": 23636,
    "CommunityResources": 6342,
    "CountDown": 8582,
    "CustomFlags": 12700,
    "DarkMode": 44,
    "DockingAlignmentDisplay": 10320,
    "EVAAnarchy": 7532,
    "EvenBetterTimeWarp": 7668,
    "FancyFuelTanks": 6676,
    "FlightPlan": 24326,
    "GalaxyTweaker": 9870,
    "HUMANS": 4154,
    "HeadUpDisplay": 10109,
    "HideOrbits": 7536,
    "IVA": 449,
    "IWishTheyMadeUICustomizable": 8488,
    "Inputbinder": 4916,
    "K2D2": 22397,
    "KESASolar": 7805,
    "KSP2PrometheusExporter": 6782,
    "Kalkulator": 7615,
    "KapybaraSpaceProgram2": 3017,
    "KerbalHeadlamp": 1483,
    "KerbalLifeHacks": 2399,
    "KerbalLifeSupportSystem": 5534,
    "KerbalNotebook": 8113,
    "KerbalSimpitKSP2": 10,
    "KerbalView": 9986,
    "KerbalWebProgram": 8132,
    "KerbolExpansion": 0,
    "KerbonautManager": 9906,
    "Kesa": 11356,
    "Konfig": 7947,
    "KontrolSystem2": 26120,
    "LazyOrbit": 17415,
    "LazyOrbitBoosted": 8205,
    "Leek": 4082,
    "LessWobbly": 9365,
    "LuxsFlamesandOrnaments": 13323,
    "LuxsOABExtensions": 9261,
    "ManeuverNodeController": 31849,
    "MapViewFocusTargeting": 8121,
    "MicroEngineer": 35301,
    "MoreResolutions": 8051,
    "NoSeizureWarning": 9761,
    "NodeManager": 23369,
    "OrbitalSurvey": 9200,
    "PaigeBGone": 9797,
    "PartsManagerHotkey": 6876,
    "PatchManager": 16162,
    "QuantumLoader": 4785,
    "QuantumModMenu": 4275,
    "QuestariaAereospace": 4478,
    "Reflektor": 212,
    "ResonantOrbitCalculator": 14239,
    "SASed-Warp": 1045,
    "SORRY": 15304,
    "SPARKTechnologies": 4515,
    "ScienceArkive": 3039,
    "ShadowIncExplorationDivision": 7724,
    "ShadowUtilityLIB": 12589,
    "Shoemaker": 1137,
    "ShowKSP2Events": 7360,
    "SkipSplashScreen": 4671,
    "SpaceWarp": 69343,
    "SpeedyStartup": 9966,
    "SuicideBurn": 0,
    "TechTreeManager": 3263,
    "TextAssetDumper": 76,
    "TexturesUtilitieseXpanded": 6874,
    "TheNuclearOption": 4897,
    "TillDusk": 7729,
    "ToggleNotifications": 9894,
    "TrimController": 347,
    "UIScaler": 9366,
    "UITKforKSP2": 36742,
    "UnityExplorer": 13668,
    "UtilityUplift": 11444,
    "WASDForVAB": 9806,
    "WMCCModules": 2108,
    "WheresMyCrewCapsule": 2203,
    "kRPC2": 7177
}