{
    "25xKerbolarSystem": 6737,
    "AlarmClock": 12721,
    "BepInEx": 113723,
    "BetterPartsManager": 0,
    "BetterPartsManagerLegacy": 0,
    "Blackskyskybox": 0,
    "BurnController": 12816,
    "CelestialGlow": 5377,
    "CheatsMenu": 0,
    "ColorPresets": 14033,
    "CommNext": 7740,
    "Commlines": 17150,
    "CommunityFixes": 37824,
    "CommunityResources": 16068,
    "CountDown": 0,
    "CustomFlags": 18328,
    "DarkMode": 1706,
    "DockingAlignmentDisplay": 20224,
    "EVAAnarchy": 12052,
    "EvenBetterTimeWarp": 12426,
    "FancyFuelTanks": 11604,
    "FlightPlan": 54326,
    "GalaxyTweaker": 14559,
    "HUMANS": 9193,
    "HeadUpDisplay": 15206,
    "HideOrbits": 12202,
    "HideVAB": 4739,
    "IVA": 1299,
    "IWishTheyMadeUICustomizable": 13969,
    "Inputbinder": 10319,
    "K2D2": 45941,
    "KESASolar": 17062,
    "KSP2PrometheusExporter": 11046,
    "Kalkulator": 12091,
    "Kapitalism": 0,
    "KapybaraSpaceProgram2": 7580,
    "KerbalHeadlamp": 8599,
    "KerbalLifeHacks": 10092,
    "KerbalLifeSupportSystem": 14420,
    "KerbalNotebook": 0,
    "KerbalSimpitKSP2": 366,
    "KerbalView": 14710,
    "KerbalWebProgram": 0,
    "KerbolExpansion": 0,
    "KerbonautManager": 15064,
    "Kesa": 21552,
    "Konfig": 0,
    "KontrolSystem2": 42433,
    "KuriosityScience": 4236,
    "LazyOrbit": 26556,
    "LazyOrbitBoosted": 13170,
    "Leek": 8459,
    "LessWobbly": 13988,
    "LuxsFlamesandOrnaments": 22949,
    "LuxsOABExtensions": 14064,
    "ManeuverNodeController": 38766,
    "MapViewFocusTargeting": 13291,
    "MicroEngineer": 55189,
    "MoreResolutions": 12394,
    "MouseFlyer": 5287,
    "NoSeizureWarning": 14416,
    "NodeManager": 46609,
    "OrbitalSurvey": 26709,
    "PaigeBGone": 14282,
    "PartsManagerHotkey": 11066,
    "PatchManager": 38995,
    "PremonitionForSpaceWarp": 15193,
    "ProbablyAskew": 5376,
    "QuantumLoader": 0,
    "QuantumModMenu": 0,
    "QuestariaAereospace": 10240,
    "QuickMods": 4174,
    "Reflektor": 622,
    "ResonantOrbitCalculator": 19816,
    "SASed-Warp": 7008,
    "SORRY": 20829,
    "SPARKTechnologies": 11004,
    "ScaledMissions": 3364,
    "ScienceArkive": 16337,
    "ShadowIncExplorationDivision": 0,
    "ShadowUtilityLIB": 0,
    "Shoemaker": 6380,
    "ShowKSP2Events": 11828,
    "SkipSplashScreen": 11402,
    "SpaceWarp": 113723,
    "SpeedyStartup": 14612,
    "SpringCleaning": 5923,
    "SuicideBurn": 0,
    "TechTreeManager": 0,
    "TextAssetDumper": 309,
    "TexturesUtilitieseXpanded": 11235,
    "TheNuclearOption": 13871,
    "TillDusk": 12140,
    "ToggleNotifications": 14462,
    "TrimController": 5246,
    "UIScaler": 14812,
    "UITKforKSP2": 62541,
    "UnityExplorer": 15255,
    "UtilityUplift": 16189,
    "VSwiFT": 6819,
    "WASDForVAB": 15921,
    "WMCCModules": 7663,
    "WayfarersWingsRankRibbons": 5841,
    "WheresMyCrewCapsule": 7616,
    "Zoomer": 3771,
    "kRPC2": 11838
}