{
    "25xKerbolarSystem": 6972,
    "AlarmClock": 13009,
    "BepInEx": 115077,
    "BetterPartsManager": 0,
    "BetterPartsManagerLegacy": 0,
    "Blackskyskybox": 0,
    "BurnController": 13015,
    "CelestialGlow": 5607,
    "CheatsMenu": 0,
    "ColorPresets": 14243,
    "CommNext": 8034,
    "Commlines": 17535,
    "CommunityFixes": 38514,
    "CommunityResources": 16416,
    "CountDown": 0,
    "CustomFlags": 18560,
    "DarkMode": 1773,
    "DockingAlignmentDisplay": 20556,
    "EVAAnarchy": 12243,
    "EvenBetterTimeWarp": 12606,
    "FancyFuelTanks": 11833,
    "FlightPlan": 55253,
    "GalaxyTweaker": 14776,
    "HUMANS": 9395,
    "HeadUpDisplay": 15394,
    "HideOrbits": 12392,
    "HideVAB": 4932,
    "IVA": 1360,
    "IWishTheyMadeUICustomizable": 14158,
    "Inputbinder": 10551,
    "K2D2": 46584,
    "KESASolar": 17381,
    "KSP2PAPI": 11549,
    "KSP2PrometheusExporter": 11208,
    "Kalkulator": 12281,
    "Kapitalism": 0,
    "KapybaraSpaceProgram2": 7760,
    "KerbalHeadlamp": 8868,
    "KerbalLifeHacks": 10338,
    "KerbalLifeSupportSystem": 14749,
    "KerbalNotebook": 0,
    "KerbalSimpitKSP2": 386,
    "KerbalView": 14896,
    "KerbalWebProgram": 0,
    "KerbolExpansion": 0,
    "KerbonautManager": 15290,
    "Kesa": 21898,
    "Konfig": 0,
    "KontrolSystem2": 42721,
    "KuriosityScience": 4475,
    "LazyOrbit": 26918,
    "LazyOrbitBoosted": 13378,
    "Leek": 8628,
    "LessWobbly": 14185,
    "LuxsFlamesandOrnaments": 23356,
    "LuxsOABExtensions": 14279,
    "ManeuverNodeController": 39313,
    "MapViewFocusTargeting": 13463,
    "MicroEngineer": 55704,
    "MoreResolutions": 12552,
    "MouseFlyer": 5486,
    "NoSeizureWarning": 14591,
    "NodeManager": 47370,
    "OrbitalSurvey": 27059,
    "PaigeBGone": 14467,
    "PartsManagerHotkey": 11216,
    "PatchManager": 39587,
    "PremonitionForSpaceWarp": 15642,
    "ProbablyAskew": 5560,
    "QuantumLoader": 0,
    "QuantumModMenu": 0,
    "QuestariaAereospace": 10483,
    "QuickMods": 4442,
    "Reflektor": 657,
    "ResonantOrbitCalculator": 20085,
    "SASed-Warp": 7206,
    "SORRY": 21076,
    "SPARKTechnologies": 11270,
    "ScaledMissions": 3555,
    "ScienceArkive": 16607,
    "ShadowIncExplorationDivision": 0,
    "ShadowUtilityLIB": 0,
    "Shoemaker": 6602,
    "ShowKSP2Events": 12002,
    "SkipSplashScreen": 11618,
    "SpaceWarp": 115077,
    "SpeedyStartup": 14793,
    "SpringCleaning": 6228,
    "SuicideBurn": 0,
    "TechTreeManager": 0,
    "TextAssetDumper": 332,
    "TexturesUtilitieseXpanded": 11424,
    "TheNuclearOption": 14234,
    "TillDusk": 12312,
    "ToggleNotifications": 14657,
    "TrimController": 5416,
    "UIScaler": 15033,
    "UITKforKSP2": 63429,
    "UnityExplorer": 15429,
    "UtilityUplift": 16397,
    "VSwiFT": 7149,
    "WASDForVAB": 16133,
    "WMCCModules": 7890,
    "WayfarersWingsRankRibbons": 6084,
    "WheresMyCrewCapsule": 7854,
    "Zoomer": 4007,
    "kRPC2": 12035
}