{
    "BepInEx": 8721,
    "BetterPartsManager": 3563,
    "BurnController": 340,
    "CheatsMenu": 4149,
    "CommunityFixes": 3348,
    "CountDown": 309,
    "CustomFlags": 3168,
    "EVAAnarchy": 149,
    "FlightPlan": 179,
    "GalaxyTweaker": 278,
    "K2D2": 902,
    "Kalkulator": 179,
    "KerbalNotebook": 317,
    "KerbalView": 915,
    "KerbalWebProgram": 215,
    "KerbonautManager": 784,
    "KontrolSystem2": 2809,
    "LazyOrbit": 7001,
    "LessWobbly": 1710,
    "LuxsOABExtensions": 187,
    "ManeuverNodeController": 6437,
    "MapViewFocusTargeting": 125,
    "MicroEngineer": 5731,
    "MoreResolutions": 302,
    "NoSeizureWarning": 627,
    "PaigeBGone": 87,
    "PartsManagerHotkey": 262,
    "ResonantOrbitCalculator": 665,
    "SORRY": 1356,
    "SpaceWarp": 8721,
    "SpeedyStartup": 627,
    "SuicideBurn": 1293,
    "UIScaler": 1971,
    "UtilityUplift": 364,
    "WASDForVAB": 2039,
    "kRPC2": 138
}