{
    "BepInEx": 33146,
    "BetterPartsManager": 10019,
    "BetterPartsManagerLegacy": 829,
    "Blackskyskybox": 21,
    "BurnController": 4918,
    "CheatsMenu": 13157,
    "Commlines": 1670,
    "CommunityFixes": 12639,
    "CommunityResources": 536,
    "CountDown": 5441,
    "CustomFlags": 8797,
    "DockingAlignmentDisplay": 2304,
    "EVAAnarchy": 4424,
    "EvenBetterTimeWarp": 4312,
    "FancyFuelTanks": 497,
    "FlightPlan": 12214,
    "GalaxyTweaker": 6690,
    "HUMANS": 589,
    "HeadUpDisplay": 6937,
    "IWishTheyMadeUICustomizable": 4567,
    "Inputbinder": 1611,
    "K2D2": 10541,
    "KESASolar": 1876,
    "KSP2PrometheusExporter": 3795,
    "Kalkulator": 4517,
    "KerbalLifeSupportSystem": 427,
    "KerbalNotebook": 5060,
    "KerbalView": 6744,
    "KerbalWebProgram": 4640,
    "KerbolExpansion": 880,
    "KerbonautManager": 5891,
    "Kesa": 5197,
    "Konfig": 4232,
    "KontrolSystem2": 17029,
    "LazyOrbit": 13561,
    "LazyOrbitBoosted": 4334,
    "Leek": 874,
    "LessWobbly": 6130,
    "LuxsFlamesandOrnaments": 6993,
    "LuxsOABExtensions": 6006,
    "ManeuverNodeController": 19880,
    "MapViewFocusTargeting": 4299,
    "MicroEngineer": 22102,
    "MoreResolutions": 4979,
    "NoSeizureWarning": 6351,
    "NodeManager": 10176,
    "PaigeBGone": 939,
    "PartsManagerHotkey": 3938,
    "PatchManager": 621,
    "QuantumLoader": 1687,
    "QuantumModMenu": 1332,
    "QuestariaAereospace": 1192,
    "ResonantOrbitCalculator": 10348,
    "SORRY": 11621,
    "SPARKTechnologies": 1075,
    "ShadowIncExplorationDivision": 4290,
    "ShadowUtilityLIB": 7369,
    "ShowKSP2Events": 4201,
    "SkipSplashScreen": 1137,
    "SpaceWarp": 33146,
    "SpeedyStartup": 6605,
    "SuicideBurn": 6565,
    "TexturesUtilitieseXpanded": 3882,
    "TheNuclearOption": 1203,
    "TillDusk": 4660,
    "ToggleNotifications": 6773,
    "UIScaler": 6173,
    "UITKforKSP2": 15564,
    "UtilityUplift": 8226,
    "WASDForVAB": 6551,
    "kRPC2": 4104
}