{
    "25xKerbolarSystem": 9319,
    "AlarmClock": 16155,
    "BepInEx": 128448,
    "BetterIcons": 2386,
    "BetterPartsManager": 0,
    "BetterPartsManagerLegacy": 0,
    "BetterUI": 2887,
    "Blackskyskybox": 0,
    "BurnController": 15140,
    "CelestialGlow": 8044,
    "CheatsMenu": 0,
    "Cloudy": 3581,
    "ColorPresets": 16380,
    "CommNext": 10884,
    "Commlines": 20562,
    "CommunityFixes": 45067,
    "CommunityResources": 19811,
    "CountDown": 0,
    "CustomFlags": 21056,
    "DarkMode": 2330,
    "DebugTools": 1033,
    "DockingAlignmentDisplay": 24060,
    "EVAAnarchy": 14207,
    "EvenBetterTimeWarp": 14798,
    "FancyFuelTanks": 14548,
    "FlightPlan": 63029,
    "GalaxyTweaker": 17089,
    "HUMANS": 11510,
    "HeadUpDisplay": 17592,
    "HideOrbits": 14267,
    "HideVAB": 6912,
    "IVA": 2163,
    "IWishTheyMadeUICustomizable": 16256,
    "Inputbinder": 12738,
    "K2D2": 52720,
    "KESASolar": 20738,
    "KSP2PAPI": 14002,
    "KSP2PrometheusExporter": 12797,
    "Kalkulator": 14217,
    "Kapitalism": 0,
    "KapybaraSpaceProgram2": 9502,
    "KerbalHeadlamp": 11267,
    "KerbalLifeHacks": 13002,
    "KerbalLifeSupportSystem": 18368,
    "KerbalNotebook": 0,
    "KerbalSimpitKSP2": 605,
    "KerbalView": 17337,
    "KerbalWebProgram": 0,
    "KerbolExpansion": 0,
    "KerbonautManager": 17612,
    "Kesa": 25767,
    "Konfig": 0,
    "KontrolSystem2": 47757,
    "Krispy": 2718,
    "KuriosityScience": 6763,
    "LazyOrbit": 30255,
    "LazyOrbitBoosted": 15541,
    "Leek": 10272,
    "LessWobbly": 16382,
    "LuxsFlamesandOrnaments": 27491,
    "LuxsOABExtensions": 16751,
    "ManeuverNodeController": 31286,
    "MapViewFocusTargeting": 15216,
    "Meltdown": 1156,
    "MicroEngineer": 61257,
    "MissionTreeExpanded": 1443,
    "MoreResolutions": 14292,
    "MouseFlyer": 7399,
    "NoSeizureWarning": 16649,
    "NodeManager": 53951,
    "OohShiny": 2246,
    "OrbitalSurvey": 30772,
    "PaigeBGone": 16497,
    "PartsManagerHotkey": 12744,
    "PatchManager": 46696,
    "Planety": 1885,
    "PremonitionForSpaceWarp": 20724,
    "ProbablyAskew": 7483,
    "QuantumLoader": 0,
    "QuantumModMenu": 0,
    "QuestariaAereospace": 13050,
    "QuickMods": 6805,
    "Reflektor": 968,
    "ResonantOrbitCalculator": 22687,
    "SASed-Warp": 9373,
    "SORRY": 23954,
    "SPARKTechnologies": 13915,
    "ScaledMissions": 5424,
    "ScienceArkive": 19359,
    "ShadowIncExplorationDivision": 0,
    "ShadowUtilityLIB": 0,
    "Shoemaker": 9859,
    "ShowKSP2Events": 13782,
    "SkipSplashScreen": 13761,
    "SpaceWarp": 128448,
    "SpeedyStartup": 16888,
    "SpringCleaning": 9574,
    "SuicideBurn": 0,
    "TechTreeManager": 0,
    "TextAssetDumper": 493,
    "TexturesUtilitieseXpanded": 13280,
    "TheISSConstructionKit": 4165,
    "TheNuclearOption": 17512,
    "TillDusk": 14148,
    "ToggleNotifications": 16571,
    "TrimController": 7252,
    "UIScaler": 17048,
    "UITKforKSP2": 72457,
    "UnityExplorer": 17748,
    "UtilityUplift": 18539,
    "VSwiFT": 10471,
    "WASDForVAB": 18449,
    "WMCCModules": 10000,
    "WayfarersWingsRankRibbons": 8277,
    "WheresMyCrewCapsule": 9977,
    "Zoomer": 6128,
    "kRPC2": 13764
}